LICENSE
MANIFEST.in
README.rst
setup.cfg
setup.py
versioneer.py
examples/__init__.py
examples/styles/__init__.py
examples/styles/default.py
examples/widgets/__init__.py
examples/widgets/badge.py
examples/widgets/base.py
examples/widgets/breadcrumb.py
examples/widgets/browser.py
examples/widgets/card.py
examples/widgets/checkbox.py
examples/widgets/combo_box.py
examples/widgets/label.py
examples/widgets/lineedit.py
examples/widgets/linetab.py
examples/widgets/loading.py
examples/widgets/menu_tab.py
examples/widgets/message.py
examples/widgets/page.py
examples/widgets/popup_message.py
examples/widgets/push_button.py
examples/widgets/radio_button.py
examples/widgets/slider.py
examples/widgets/slider_panel.py
examples/widgets/spinbox.py
examples/widgets/switch.py
examples/widgets/toast.py
examples/widgets/tool_button.py
examples/widgets/toolbar.py
tests/__init__.py
tests/test_general.py
tpDcc/__init__.py
tpDcc/libs/__init__.py
tpDcc/libs/qt/__init__.py
tpDcc/libs/qt/__logging__.ini
tpDcc/libs/qt/__version__.py
tpDcc/libs/qt/_version.py
tpDcc/libs/qt/loader.py
tpDcc/libs/qt/core/__init__.py
tpDcc/libs/qt/core/animation.py
tpDcc/libs/qt/core/awesome.py
tpDcc/libs/qt/core/base.py
tpDcc/libs/qt/core/config.py
tpDcc/libs/qt/core/consts.py
tpDcc/libs/qt/core/contexts.py
tpDcc/libs/qt/core/decorators.py
tpDcc/libs/qt/core/dpi.py
tpDcc/libs/qt/core/dragger.py
tpDcc/libs/qt/core/formatters.py
tpDcc/libs/qt/core/image.py
tpDcc/libs/qt/core/input.py
tpDcc/libs/qt/core/menu.py
tpDcc/libs/qt/core/mixin.py
tpDcc/libs/qt/core/observable.py
tpDcc/libs/qt/core/preferences.py
tpDcc/libs/qt/core/qtutils.py
tpDcc/libs/qt/core/resizers.py
tpDcc/libs/qt/core/settings.py
tpDcc/libs/qt/core/statusbar.py
tpDcc/libs/qt/core/timers.py
tpDcc/libs/qt/core/tool.py
tpDcc/libs/qt/core/traymessage.py
tpDcc/libs/qt/core/utils.py
tpDcc/libs/qt/core/worker.py
tpDcc/libs/qt/managers/__init__.py
tpDcc/libs/qt/managers/inputs.py
tpDcc/libs/qt/managers/toolsets.py
tpDcc/libs/qt/widgets/__init__.py
tpDcc_libs_qt.egg-info/PKG-INFO
tpDcc_libs_qt.egg-info/SOURCES.txt
tpDcc_libs_qt.egg-info/dependency_links.txt
tpDcc_libs_qt.egg-info/not-zip-safe
tpDcc_libs_qt.egg-info/requires.txt
tpDcc_libs_qt.egg-info/top_level.txt