Metadata-Version: 2.1
Name: tpDcc-libs-qt
Version: 0.0.22
Summary: Collection of Python utilities modules to work with PySide/PyQt and DCCs
Home-page: https://github.com/tpDcc/tpDcc-libs-qt
Author: Tomas Poveda
Author-email: tpovedatd@gmail.com
License: MIT
Platform: UNKNOWN
Provides-Extra: dev
Provides-Extra: test
